CHANGES.rst
DESCRIPTION.rst
LICENSE
MANIFEST.in
README.md
setup.py
src/sdc/vis/class_lister.py
src/sdc/vis/filter/__init__.py
src/sdc/vis/reader/__init__.py
src/sdc/vis/writer/__init__.py
src/sdc/vis/writer/_view_spectra.py
src/spectral_data_converter_vis.egg-info/PKG-INFO
src/spectral_data_converter_vis.egg-info/SOURCES.txt
src/spectral_data_converter_vis.egg-info/dependency_links.txt
src/spectral_data_converter_vis.egg-info/entry_points.txt
src/spectral_data_converter_vis.egg-info/requires.txt
src/spectral_data_converter_vis.egg-info/top_level.txt