Metadata-Version: 2.1
Name: spectral-data-converter-vis
Version: 0.0.1
Summary: Visualization plugins for the spectral-data-converter library.
Home-page: https://github.com/waikato-datamining/spectral-data-converter-vis
Author: Peter Reutemann
Author-email: fracpete@waikato.ac.nz
License: MIT License
Classifier: Development Status :: 4 - Beta
Classifier: License :: OSI Approved :: MIT License
Classifier: Topic :: Scientific/Engineering
Classifier: Topic :: Scientific/Engineering :: Visualization
License-File: LICENSE
